{
  "title": "Battlezoo Bestiary for Pathfinder 2e by Roll For Combat",
  "description": "The Battlezoo Bestiary for Pathfinder Second Edition contains 114 award-winning monsters, the Monster Parts system, the Monster Mage and Vestige Hunter archetypes, new backgrounds, magic items, and more!",
  "authors": [
    {
      "name": "Stephen Glicker, Patrick Renie, and Mark Seifter",
      "flags": {}
    }
  ],
  "url": "http://www.battlezoo.com",
  "flags": {
    "battlezoo-bestiary-pf2e": {
      "pf2e-homebrew": {
        "baseWeapons": {
          "galtzagorri-hook-spear": "Galtzagorri Hook Spear"
        },
        "creatureTraits": {
          "dundrath": {
            "label": "Dundrath",
            "description": "Dundraths are thickset humanoids who resemble woolly mammoths except for their burly arms and hands and keen yellow eyes."
          },
          "gmayun": {
            "label": "G'Mayun",
            "description": "G'mayuns are avian humanoids that resemble colorful parrots and other birds native to tropical paradises."
          },
          "husk": {
            "label": "Husk",
            "description": "Plant creatures share a special bond with the natural world that few other beings can completely understand or appreciate. When the bond to its realm is broken or severed, a sentient plant creature’s rage can transform it into a terrible shadow of its former self. Benign and even friendly plants like leshies, arboreals, and dryads all run the risk of this horrible metamorphosis, though their own agony often pales in comparison to the horrors which they inflict on their victims. Lonely, angry, and twisted, plant husks sow their monstrous madness in the fertile corpses of wanderers who dare travel through the husk’s blighted swath of wilderness. Though in their eyes any living creature is worthy of obliteration, husks reserve their most horrendous punishments for any litterer, land settler, or lumberjack who ever dared to desecrate, dominate, or denude the forest."
          },
          "wild-hunt": {
            "label": "Wild Hunt",
            "description": "The wild hunt is a group of enigmatic fey who hunt prey across not only the fey realm, but across the entire multiverse."
          }
        },
        "weaponTraits": {
          "injury": {
            "label": "PF2E.TraitInjury",
            "description": "PF2E.TraitDescriptionInjury"
          }
        }
      }
    }
  },
  "version": "1.1",
  "compatibility": {
    "minimum": "10",
    "verified": "10"
  },
  "packs": [
    {
      "label": "Battlezoo Bestiary - Creatures",
      "type": "Actor",
      "name": "pf2e-battlezoo-bestiary",
      "path": "packs/pf2e-battlezoo-bestiary.db",
      "system": "pf2e",
      "private": false,
      "flags": {}
    },
    {
      "label": "Battlezoo Bestiary - Effects",
      "type": "Item",
      "name": "pf2e-battlezoo-bestiary-effects",
      "path": "packs/pf2e-battlezoo-bestiary-effects.db",
      "system": "pf2e",
      "private": false,
      "flags": {}
    },
    {
      "label": "Battlezoo Bestiary - Equipment",
      "type": "Item",
      "name": "pf2e-battlezoo-equipment",
      "path": "packs/pf2e-battlezoo-equipment.db",
      "system": "pf2e",
      "private": false,
      "flags": {}
    },
    {
      "label": "Battlezoo Bestiary - Feats",
      "type": "Item",
      "name": "pf2e-battlezoo-feats-and-actions",
      "path": "packs/pf2e-battlezoo-feats-and-actions.db",
      "system": "pf2e",
      "private": false,
      "flags": {}
    },
    {
      "label": "Battlezoo Bestiary - Actions",
      "type": "Item",
      "name": "pf2e-battlezoo-actions",
      "path": "packs/pf2e-battlezoo-actions.db",
      "system": "pf2e",
      "private": false,
      "flags": {}
    },
    {
      "label": "Battlezoo Bestiary - Backgrounds",
      "type": "Item",
      "name": "pf2e-battlezoo-backgrounds",
      "path": "packs/pf2e-battlezoo-backgrounds.db",
      "system": "pf2e",
      "private": false,
      "flags": {}
    },
    {
      "label": "Battlezoo Bestiary",
      "type": "JournalEntry",
      "name": "pf2e-battlezoo-monster-parts",
      "path": "packs/pf2e-battlezoo-monster-parts-subsystem.db",
      "system": "pf2e",
      "private": false,
      "flags": {}
    },
    {
      "label": "Battlezoo Bestiary - Macros",
      "type": "Macro",
      "name": "pf2e-battlezoo-bestiary-macros",
      "path": "packs/pf2e-battlezoo-bestiary-macros.db",
      "system": "pf2e",
      "private": false,
      "flags": {}
    }
  ],
  "relationships": {
    "systems": [
      {
        "id": "pf2e",
        "type": "system",
        "manifest": "https://github.com/foundryvtt/pf2e/releases/latest/download/system.json",
        "compatibility": {
          "minimum": "4.0.6"
        }
      }
    ]
  },
  "id": "battlezoo-bestiary-pf2e",
  "manifest": "https://foundryvtt.s3.us-west-2.amazonaws.com/modules/battlezoo-bestiary-pf2e/module.json"
}